{
 "cells": [
  {
   "cell_type": "markdown",
   "metadata": {},
   "source": [
    "### 2.6 시퀀스의 복합 할당\n",
    "+= 연산자가 작동하도록 만드는 특수 메서드: ```__iadd__()```. 구현되어있지 않은 경우 ```__add__()```\n",
    "\n",
    "*= 연산자가 작동하도록 만드는 특수 메서드: ```__imul__()```\n",
    "\n",
    "*참고: 메서드명에서 i는 in-place를 의미하며 해당 변수를 직접 변경한다.*"
   ]
  },
  {
   "cell_type": "code",
   "execution_count": 3,
   "metadata": {},
   "outputs": [
    {
     "name": "stdout",
     "output_type": "stream",
     "text": [
      "2175024196736\n",
      "[1, 2, 3, 1, 2, 3]\n",
      "2175024196736\n"
     ]
    }
   ],
   "source": [
    "l = [1, 2, 3]\n",
    "print(id(l))\n",
    "l *= 2\n",
    "print(l)\n",
    "print(id(l))"
   ]
  },
  {
   "cell_type": "code",
   "execution_count": 5,
   "metadata": {},
   "outputs": [
    {
     "name": "stdout",
     "output_type": "stream",
     "text": [
      "2174971671936\n",
      "(1, 2, 3, 1, 2, 3)\n",
      "2174972527424\n"
     ]
    }
   ],
   "source": [
    "t = (1, 2, 3)\n",
    "print(id(t))\n",
    "t *= 2\n",
    "print(t)\n",
    "print(id(t)) # 불변시퀀스의 경우 새로운 튜플 객체가 만들어짐."
   ]
  },
  {
   "cell_type": "markdown",
   "metadata": {},
   "source": [
    "#### 2.6.1 += 복합 할당 퀴즈\n",
    "[예제 2-14] 퀴즈 (연산이 수행 되고 TypeError도 발생한다.)"
   ]
  },
  {
   "cell_type": "code",
   "execution_count": 9,
   "metadata": {},
   "outputs": [
    {
     "ename": "TypeError",
     "evalue": "'tuple' object does not support item assignment",
     "output_type": "error",
     "traceback": [
      "\u001b[1;31m---------------------------------------------------------------------------\u001b[0m",
      "\u001b[1;31mTypeError\u001b[0m                                 Traceback (most recent call last)",
      "\u001b[1;32m~\\AppData\\Local\\Temp/ipykernel_3152/1891221013.py\u001b[0m in \u001b[0;36m<module>\u001b[1;34m\u001b[0m\n\u001b[0;32m      1\u001b[0m \u001b[0mt\u001b[0m \u001b[1;33m=\u001b[0m \u001b[1;33m(\u001b[0m\u001b[1;36m1\u001b[0m\u001b[1;33m,\u001b[0m \u001b[1;36m2\u001b[0m\u001b[1;33m,\u001b[0m \u001b[1;33m[\u001b[0m\u001b[1;36m30\u001b[0m\u001b[1;33m,\u001b[0m \u001b[1;36m40\u001b[0m\u001b[1;33m]\u001b[0m\u001b[1;33m)\u001b[0m\u001b[1;33m\u001b[0m\u001b[1;33m\u001b[0m\u001b[0m\n\u001b[1;32m----> 2\u001b[1;33m \u001b[0mt\u001b[0m\u001b[1;33m[\u001b[0m\u001b[1;36m2\u001b[0m\u001b[1;33m]\u001b[0m \u001b[1;33m+=\u001b[0m \u001b[1;33m[\u001b[0m\u001b[1;36m50\u001b[0m\u001b[1;33m,\u001b[0m \u001b[1;36m60\u001b[0m\u001b[1;33m]\u001b[0m\u001b[1;33m\u001b[0m\u001b[1;33m\u001b[0m\u001b[0m\n\u001b[0m",
      "\u001b[1;31mTypeError\u001b[0m: 'tuple' object does not support item assignment"
     ]
    }
   ],
   "source": [
    "t = (1, 2, [30, 40])\n",
    "t[2] += [50, 60]"
   ]
  },
  {
   "cell_type": "code",
   "execution_count": 10,
   "metadata": {},
   "outputs": [
    {
     "data": {
      "text/plain": [
       "(1, 2, [30, 40, 50, 60])"
      ]
     },
     "execution_count": 10,
     "metadata": {},
     "output_type": "execute_result"
    }
   ],
   "source": [
    "t"
   ]
  },
  {
   "cell_type": "markdown",
   "metadata": {},
   "source": [
    "[예제 2-16] s[a] += b 표현식에 대한 바이트코드"
   ]
  },
  {
   "cell_type": "code",
   "execution_count": 11,
   "metadata": {},
   "outputs": [
    {
     "name": "stdout",
     "output_type": "stream",
     "text": [
      "  1           0 LOAD_NAME                0 (s)\n",
      "              2 LOAD_NAME                1 (a)\n",
      "              4 DUP_TOP_TWO\n",
      "              6 BINARY_SUBSCR\n",
      "              8 LOAD_NAME                2 (b)\n",
      "             10 INPLACE_ADD\n",
      "             12 ROT_THREE\n",
      "             14 STORE_SUBSCR\n",
      "             16 LOAD_CONST               0 (None)\n",
      "             18 RETURN_VALUE\n"
     ]
    }
   ],
   "source": [
    "import dis\n",
    "dis.dis('s[a] += b')"
   ]
  },
  {
   "cell_type": "code",
   "execution_count": null,
   "metadata": {},
   "outputs": [],
   "source": [
    "#   1           0 LOAD_NAME                0 (s)\n",
    "#               2 LOAD_NAME                1 (a)\n",
    "#               4 DUP_TOP_TWO\n",
    "#               6 BINARY_SUBSCR   *s[a] 값을 Top of Stack (TOS)에 놓음.*\n",
    "#               8 LOAD_NAME                2 (b)\n",
    "#              10 INPLACE_ADD   *TOS+=b 연산을 수행. TOS가 가변 객체를 가리키면 이 연산은 성공함.*\n",
    "#              12 ROT_THREE\n",
    "#              14 STORE_SUBSCR  *TOS를 s[a]에 할당. s가 불변객체면 실패함.*\n",
    "#              16 LOAD_CONST               0 (None)\n",
    "#              18 RETURN_VALUE"
   ]
  }
 ],
 "metadata": {
  "interpreter": {
   "hash": "a5d039ad54531960e989e2b1d6b78f0f66143650014cda642577cb22d2138647"
  },
  "kernelspec": {
   "display_name": "Python 3.9.7 64-bit ('base': conda)",
   "language": "python",
   "name": "python3"
  },
  "language_info": {
   "codemirror_mode": {
    "name": "ipython",
    "version": 3
   },
   "file_extension": ".py",
   "mimetype": "text/x-python",
   "name": "python",
   "nbconvert_exporter": "python",
   "pygments_lexer": "ipython3",
   "version": "3.9.7"
  },
  "orig_nbformat": 4
 },
 "nbformat": 4,
 "nbformat_minor": 2
}
